tbot/__init__.py
tbot/activation.py
tbot/apps.py
tbot/bot.py
tbot/commands.py
tbot/configs.py
tbot/error_handler.py
tbot/exception.py
tbot/handler.py
tbot/serializers.py
tbot/urls.py
tbot/utils.py
tbot/views.py
django_tbot-0.0.1.dist-info/AUTHORS.rst
django_tbot-0.0.1.dist-info/LICENSE
django_tbot-0.0.1.dist-info/METADATA
django_tbot-0.0.1.dist-info/WHEEL
django_tbot-0.0.1.dist-info/top_level.txt
django_tbot-0.0.1.dist-info/RECORD
