Metadata-Version: 2.1
Name: django-tbot
Version: 0.0.1
Summary: Telegram Bot implementation for Django Framework
Home-page: https://github.com/vahedashyan/django-tbot
Author: Vahe Dashyan
Author-email: vahedashyan@gmail.com
License: BSD
Platform: UNKNOWN
Classifier: Development Status :: 3 - Alpha
Classifier: Environment :: Web Environment
Classifier: Intended Audience :: Developers
Classifier: License :: OSI Approved :: GNU Affero General Public License v3
Classifier: Operating System :: OS Independent
Classifier: Programming Language :: Python :: 3
Classifier: Programming Language :: Python :: 3.6
Classifier: Programming Language :: Python :: 3.7
Classifier: Programming Language :: Python :: 3.8
Classifier: Framework :: Django
Classifier: Framework :: Django :: 2.0
Classifier: Framework :: Django :: 2.1
Classifier: Framework :: Django :: 2.2
Requires-Dist: python-telegram-bot (==12.4.2)
Requires-Dist: requests (==2.23.0)
